glossary.tsv
grammar.json
yar_numerals/__init__.py
yar_numerals/__main__.py
yar_numerals/cardinals.py
yar_numerals/conf.py
yar_numerals/decimals.py
yar_numerals/errors.py
yar_numerals/fractionals.py
yar_numerals/grammar.py
yar_numerals/grapheme.py
yar_numerals/index.rst
yar_numerals/lexeme/__init__.py
yar_numerals/lexeme/numeral/cardinal.py
yar_numerals/lexeme/numeral/cardinal_stem.py
yar_numerals/lexeme/numeral/misc.py
yar_numerals/lexeme/numeral/ordinal.py
yar_numerals/ordinals.py
yar_numerals/syntax/__init__.py
yar_numerals/syntax/relation.py
yar_numerals/test_cardinal_lexemes.py
yar_numerals/test_cardinals.py
yar_numerals/test_decimals.py
yar_numerals/test_fractionals.py
yar_numerals/test_grapheme.py
yar_numerals/test_main.py
yar_numerals/test_ordinals.py
yar_numerals/validator.py
yar_numerals-1.0.4.dist-info/LICENSE
yar_numerals-1.0.4.dist-info/METADATA
yar_numerals-1.0.4.dist-info/WHEEL
yar_numerals-1.0.4.dist-info/entry_points.txt
yar_numerals-1.0.4.dist-info/RECORD
