Metadata-Version: 2.1
Name: yar-numerals
Version: 1.0.4
Summary: Number to text - Inflector for Ukrainian numerals
Home-page: https://yar.org.ua/
License: MIT-0
Keywords: NLP,Ukrainian,numerals,spelling,text,numbers,uk,syntax
Author: Yar team
Author-email: team@yar.org.ua
Requires-Python: >=3.7,<3.12
Classifier: License :: OSI Approved
Classifier: License :: OSI Approved :: MIT No Attribution License (MIT-0)
Classifier: Natural Language :: Ukrainian
Classifier: Operating System :: OS Independent
Classifier: Programming Language :: Python :: 3
Classifier: Programming Language :: Python :: 3.7
Classifier: Programming Language :: Python :: 3.8
Classifier: Programming Language :: Python :: 3.9
Classifier: Programming Language :: Python :: 3.10
Classifier: Programming Language :: Python :: 3.11
Classifier: Topic :: Text Processing :: Linguistic
Project-URL: Documentation, http://yar.ua.gitlab.io/numerals.py/
Project-URL: Repository, https://gitlab.com/yar.ua/numerals.py/
